toynet/__init__.py
toynet/config.py
toynet/data_loaders/__init__.py
toynet/data_loaders/basic_data_loader.py
toynet/data_loaders/csv_data_loader.py
toynet/data_loaders/protocol.py
toynet/functions/__init__.py
toynet/functions/abstract.py
toynet/functions/activation.py
toynet/functions/loss.py
toynet/initalizers/__init__.py
toynet/initalizers/abstract.py
toynet/initalizers/he.py
toynet/initalizers/xavier.py
toynet/layers/__init__.py
toynet/layers/dense.py
toynet/layers/protocol.py
toynet/networks/__init__.py
toynet/networks/mlp.py
toynet/networks/protocol.py
toynet/optimizers/__init__.py
toynet/optimizers/adam.py
toynet/optimizers/basic_optimizer.py
toynet/optimizers/protocol.py
toynet/policies/__init__.py
toynet/policies/periodically_save_model.py
toynet/policies/protocol.py
toynet/policies/reduce_lr_on_plateu.py
toynet/policies/save_best_model.py
toynet/policies/validation_early_stop.py
toynet_ml-1.0.0.dist-info/licenses/LICENSE
toynet_ml-1.0.0.dist-info/METADATA
toynet_ml-1.0.0.dist-info/WHEEL
toynet_ml-1.0.0.dist-info/top_level.txt
toynet_ml-1.0.0.dist-info/RECORD
