Metadata-Version: 2.4
Name: toynet-ml
Version: 1.0.0
Summary: An educational but robust deep learning framework implemented from scratch using NumPy.
Author: Maciej Kmieć
Keywords: deep learning,machine learning,neural networks,numpy,artificial intelligence,framework,education
Requires-Python: >=3.12
License-File: LICENSE
Requires-Dist: numpy>=2.3.2
Requires-Dist: pandas>=2.3.1
Provides-Extra: dev
Requires-Dist: pytest>=8.4.1; extra == "dev"
Requires-Dist: pytest-cov>=6.2.1; extra == "dev"
Requires-Dist: ruff>=0.12.8; extra == "dev"
Requires-Dist: mypy>=1.17.1; extra == "dev"
Requires-Dist: pip-tools>=7.5.0; extra == "dev"
Dynamic: license-file
